MANIFEST.in
README.rst
setup.py
Markdown_Bugzilla_Extension.egg-info/PKG-INFO
Markdown_Bugzilla_Extension.egg-info/SOURCES.txt
Markdown_Bugzilla_Extension.egg-info/dependency_links.txt
Markdown_Bugzilla_Extension.egg-info/top_level.txt
mdbz/__init__.py
mdbz/extension.py
mdbz/rhbz.py
mdbz/tests.py